telfhk0/telfhk0.py
telfhk0-0.1.1.dist-info/METADATA
telfhk0-0.1.1.dist-info/WHEEL
telfhk0-0.1.1.dist-info/top_level.txt
telfhk0-0.1.1.dist-info/RECORD
