Metadata-Version: 2.1
Name: telfhk0
Version: 0.1.1
Summary: Telegram for Hackers
Home-page: https://github.com/esfelurm/telfhk6
Download-URL: https://github.com/esfelurm/telfhk6/archive/v_0.0.1.tar.gz
Author: Esfelurm
Author-email: esfelurm@yahoo.com
Project-URL: Documentation, https://t.me/TelFHk
Keywords: ..:::EsFeLuRm:::..
Classifier: Development Status :: 3 - Alpha
Classifier: Intended Audience :: Developers
Classifier: Topic :: Software Development :: Build Tools
Classifier: Programming Language :: Python :: 3
Classifier: Programming Language :: Python :: 3.4
Classifier: Programming Language :: Python :: 3.5
Classifier: Programming Language :: Python :: 3.6
Requires-Dist: colorama ==0.4.6
